lara_sdk/__init__.py
lara_sdk/_client.py
lara_sdk/_credentials.py
lara_sdk/_errors.py
lara_sdk/_s3client.py
lara_sdk/_translator.py
lara_sdk-1.6.3.dist-info/licenses/LICENSE
lara_sdk-1.6.3.dist-info/METADATA
lara_sdk-1.6.3.dist-info/WHEEL
lara_sdk-1.6.3.dist-info/top_level.txt
lara_sdk-1.6.3.dist-info/RECORD
