Metadata-Version: 2.4
Name: lara-sdk
Version: 1.6.3
Summary: A Python library for Lara's API.
Author-email: Translated <support@laratranslate.com>
Maintainer-email: Translated <support@laratranslate.com>
Project-URL: Homepage, https://laratranslate.com/
Project-URL: Source, https://github.com/translated/lara-python
Classifier: Programming Language :: Python :: 3
Classifier: License :: OSI Approved :: MIT License
Classifier: Operating System :: OS Independent
Requires-Python: >=3.8
License-File: LICENSE
Requires-Dist: requests
Requires-Dist: gzip-stream
Dynamic: license-file
